rabbitmq_toolkit/__init__.py
rabbitmq_toolkit/consumer.py
rabbitmq_toolkit/producer.py
rabbitmq_toolkit/queue_manager.py
rabbitmq_toolkit-0.1.7.dist-info/METADATA
rabbitmq_toolkit-0.1.7.dist-info/WHEEL
rabbitmq_toolkit-0.1.7.dist-info/top_level.txt
rabbitmq_toolkit-0.1.7.dist-info/RECORD
