Metadata-Version: 2.1
Name: rabbitmq_toolkit
Version: 0.1.7
Summary: A streamlined toolkit for efficient RabbitMQ operations.
Home-page: https://github.com/your_username/rabbitmq_toolkit
Author: Infinity Team
Keywords: rabbitmq,messaging,queue,producer,consumer
Classifier: Programming Language :: Python :: 3
Classifier: License :: OSI Approved :: MIT License
Classifier: Operating System :: OS Independent
Requires-Python: >=3.6
Requires-Dist: pika
